fuzzyometry/__init__.py
fuzzyometry/_version.py
fuzzyometry/bodies.py
fuzzyometry/combinations.py
fuzzyometry/threads.py
fuzzyometry-0.0.6.dist-info/METADATA
fuzzyometry-0.0.6.dist-info/WHEEL
fuzzyometry-0.0.6.dist-info/RECORD
